ubii/proto/__init__.py
ubii/proto/util.py
ubii/proto/v1/__init__.py
ubii/proto/v1/clients/__init__.py
ubii/proto/v1/clients/client.proto
ubii/proto/v1/clients/client_pb_plus.py
ubii/proto/v1/dataStructure/__init__.py
ubii/proto/v1/dataStructure/buttonEventType.proto
ubii/proto/v1/dataStructure/buttonEventType_pb_plus.py
ubii/proto/v1/dataStructure/color.proto
ubii/proto/v1/dataStructure/color_pb_plus.py
ubii/proto/v1/dataStructure/handGestureType.proto
ubii/proto/v1/dataStructure/handGestureType_pb_plus.py
ubii/proto/v1/dataStructure/image.proto
ubii/proto/v1/dataStructure/image_pb_plus.py
ubii/proto/v1/dataStructure/keyEvent.proto
ubii/proto/v1/dataStructure/keyEvent_pb_plus.py
ubii/proto/v1/dataStructure/lists.proto
ubii/proto/v1/dataStructure/lists_pb_plus.py
ubii/proto/v1/dataStructure/matrix3x2.proto
ubii/proto/v1/dataStructure/matrix3x2_pb_plus.py
ubii/proto/v1/dataStructure/matrix4x4.proto
ubii/proto/v1/dataStructure/matrix4x4_pb_plus.py
ubii/proto/v1/dataStructure/mouseEvent.proto
ubii/proto/v1/dataStructure/mouseEvent_pb_plus.py
ubii/proto/v1/dataStructure/myoEvent.proto
ubii/proto/v1/dataStructure/myoEvent_pb_plus.py
ubii/proto/v1/dataStructure/object2d.proto
ubii/proto/v1/dataStructure/object2d_pb_plus.py
ubii/proto/v1/dataStructure/object3d.proto
ubii/proto/v1/dataStructure/object3d_pb_plus.py
ubii/proto/v1/dataStructure/pose2d.proto
ubii/proto/v1/dataStructure/pose2d_pb_plus.py
ubii/proto/v1/dataStructure/pose3d.proto
ubii/proto/v1/dataStructure/pose3d_pb_plus.py
ubii/proto/v1/dataStructure/quaternion.proto
ubii/proto/v1/dataStructure/quaternion_pb_plus.py
ubii/proto/v1/dataStructure/touchEvent.proto
ubii/proto/v1/dataStructure/touchEvent_pb_plus.py
ubii/proto/v1/dataStructure/vector2.proto
ubii/proto/v1/dataStructure/vector2_pb_plus.py
ubii/proto/v1/dataStructure/vector3.proto
ubii/proto/v1/dataStructure/vector3_pb_plus.py
ubii/proto/v1/dataStructure/vector4.proto
ubii/proto/v1/dataStructure/vector4_pb_plus.py
ubii/proto/v1/dataStructure/vector8.proto
ubii_message_formats-0.3.0.dist-info/LICENSE
ubii_message_formats-0.3.0.dist-info/METADATA
ubii_message_formats-0.3.0.dist-info/WHEEL
ubii_message_formats-0.3.0.dist-info/proto_package.txt
ubii_message_formats-0.3.0.dist-info/top_level.txt
ubii_message_formats-0.3.0.dist-info/RECORD
