Metadata-Version: 2.1
Name: ubii-message-formats
Version: 0.3.0
Summary: "Python Code for Ubi Interact protobuf messages"
Home-page: https://github.com/saggitar/ubii-msg-formats.git
Author: Maximilian Schmidt
Author-email: ga97lul@mytum.de
Keywords: ubii,ubi-interact,protobuf,proto-plus
Classifier: Programming Language :: Python :: 3
Requires-Python: >=3.7
License-File: LICENSE
Requires-Dist: proto-plus (>=1.20.6)
Requires-Dist: protobuf (==3.20.1)
Requires-Dist: generic-proto-plus-stubs (>=0.3)
Requires-Dist: more-itertools
Provides-Extra: compiler
Requires-Dist: codestare-msg-compiler[protoplus] (>=0.0.6) ; extra == 'compiler'
Provides-Extra: docs
Requires-Dist: sphinx (==4.2.0) ; extra == 'docs'
Requires-Dist: importlib-metadata ; (python_version < "3.8") and extra == 'docs'
Provides-Extra: test
Requires-Dist: pytest ; extra == 'test'
